odoo10_addon_product_sequence-10.0.1.0.0-py2.7-nspkg.pth
odoo10_addon_product_sequence-10.0.1.0.0.dist-info/top_level.txt
odoo10_addon_product_sequence-10.0.1.0.0.dist-info/WHEEL
odoo10_addon_product_sequence-10.0.1.0.0.dist-info/RECORD
odoo10_addon_product_sequence-10.0.1.0.0.dist-info/metadata.json
odoo10_addon_product_sequence-10.0.1.0.0.dist-info/DESCRIPTION.rst
odoo10_addon_product_sequence-10.0.1.0.0.dist-info/METADATA
odoo10_addon_product_sequence-10.0.1.0.0.dist-info/namespace_packages.txt
odoo/addons/product_sequence/__manifest__.py
odoo/addons/product_sequence/hooks.py
odoo/addons/product_sequence/__init__.py
odoo/addons/product_sequence/README.rst
odoo/addons/product_sequence/models/product_product.py
odoo/addons/product_sequence/models/__init__.py
odoo/addons/product_sequence/i18n/product_sequence.pot
odoo/addons/product_sequence/i18n/es.po
odoo/addons/product_sequence/i18n/ca.po
odoo/addons/product_sequence/i18n/de.po
odoo/addons/product_sequence/data/product_sequence.xml
odoo/addons/product_sequence/tests/__init__.py
odoo/addons/product_sequence/tests/test_product_sequence.py
odoo/addons/product_sequence/static/description/icon.png
